hydrosdk/__init__.py
hydrosdk/application.py
hydrosdk/builder.py
hydrosdk/cluster.py
hydrosdk/data/__init__.py
hydrosdk/data/conversions.py
hydrosdk/data/types.py
hydrosdk/deployment_configuration.py
hydrosdk/exceptions.py
hydrosdk/image.py
hydrosdk/modelversion.py
hydrosdk/monitoring.py
hydrosdk/predictor.py
hydrosdk/servable.py
hydrosdk/signature.py
hydrosdk/utils.py
hydrosdk-3.0.3.dist-info/LICENSE
hydrosdk-3.0.3.dist-info/WHEEL
hydrosdk-3.0.3.dist-info/METADATA
hydrosdk-3.0.3.dist-info/RECORD
